stickytoe_device/__init__.py
stickytoe_device/constants.py
stickytoe_device/devices.py
stickytoe_device/inputs.py
stickytoe_device/bin/pip
stickytoe_device-0.0.4.dist-info/LICENSE
stickytoe_device-0.0.4.dist-info/METADATA
stickytoe_device-0.0.4.dist-info/WHEEL
stickytoe_device-0.0.4.dist-info/top_level.txt
stickytoe_device-0.0.4.dist-info/RECORD
