Metadata-Version: 2.1
Name: stickytoe-device
Version: 0.0.4
Summary: Stickytoe device abstract class and constants
Home-page: https://github.com/ryanchaiyakul/stickytoe_device
Author: Ryan Chaiyakul
License: UNKNOWN
Platform: UNKNOWN
Classifier: Programming Language :: Python :: 3
Classifier: License :: OSI Approved :: MIT License
Classifier: Operating System :: OS Independent
Requires-Python: >=3.6
